{
	"windturbine": {
		"inputs": {
			"labor": 1
		},
		"outputs": {
			"electricity": 200
		}
	},
	"minesmall": {
		"inputs": {
			"electricity": 120,
			"labor": 3
		},
		"outputs": {
			"minerals": 18
		}
	},
	"factorysmall": {
		"steel" :{
			"inputs": {
				"electricity": 120,
				"labor": 3,
				"iron": 150,
				"coal": 300
			},
			"outputs": {
				"steel": 150
			}
		},
		"concrete": {
			"inputs": {
				"electricity": 120,
				"labor": 3,
				"stone": 3
			},
			"outputs": {
				"concrete": 3
			}
		},
		"glass": {
			"inputs": {
				"electricity": 120,
				"labor": 3,
				"minerals": 20
			},
			"outputs": {
				"glass": 20
			}
		}
	}
}